kallisto/__init__.py
kallisto/atom.py
kallisto/console.py
kallisto/data/__init__.py
kallisto/data/alpha.py
kallisto/data/vdw.py
kallisto/grid.py
kallisto/methods.py
kallisto/molecule.py
kallisto/reader/__init__.py
kallisto/reader/strucreader.py
kallisto/reader/turbomole.py
kallisto/reader/xyz.py
kallisto/rmsd.py
kallisto/sort.py
kallisto/sterics.py
kallisto/units.py
kallisto/utils/__init__.py
kallisto/utils/alpha.py
kallisto-1.0.10.dist-info/LICENSE
kallisto-1.0.10.dist-info/WHEEL
kallisto-1.0.10.dist-info/entry_points.txt
kallisto-1.0.10.dist-info/METADATA
kallisto-1.0.10.dist-info/RECORD
