Metadata-Version: 2.1
Name: kallisto
Version: 1.0.10
Summary: The Kallisto software enables the efficient calculation of atomic features that can be used within a quantitative structure-activity relationship (QSAR) approach. Furthermore, several modelling helpers are implemented.
Home-page: https://github.com/AstraZeneca/kallisto
License: Apache 2.0
Keywords: chemistry,computational-chemistry,quantum-chemistry,machinelearning
Author: Eike Caldeweyher
Author-email: hello@eikecaldeweyher.de
Requires-Python: >=3.10,<3.13
Classifier: License :: Other/Proprietary License
Classifier: Programming Language :: Python :: 3
Classifier: Programming Language :: Python :: 3.10
Classifier: Programming Language :: Python :: 3.11
Requires-Dist: click (>=8.0.0,<9.0.0)
Requires-Dist: numpy (>=1.19.0,<2.0.0)
Requires-Dist: scipy (>=1.10.0,<2.0.0)
Project-URL: Repository, https://github.com/AstraZeneca/kallisto
